rstring/__init__.py
rstring/__main__.py
rstring/cli.py
rstring/git.py
rstring/tree.py
rstring/utils.py
rstring-0.4.1.dist-info/licenses/LICENSE
tests/__init__.py
tests/test_rstring.py
rstring-0.4.1.dist-info/METADATA
rstring-0.4.1.dist-info/WHEEL
rstring-0.4.1.dist-info/entry_points.txt
rstring-0.4.1.dist-info/top_level.txt
rstring-0.4.1.dist-info/RECORD
